pyngb/__init__.py
pyngb/__main__.py
pyngb/baseline.py
pyngb/batch.py
pyngb/constants.py
pyngb/exceptions.py
pyngb/py.typed
pyngb/util.py
pyngb/validation.py
pyngb/analysis/__init__.py
pyngb/analysis/dtg.py
pyngb/api/__init__.py
pyngb/api/analysis.py
pyngb/api/loaders.py
pyngb/api/metadata.py
pyngb/binary/__init__.py
pyngb/binary/handlers.py
pyngb/binary/parser.py
pyngb/core/__init__.py
pyngb/core/parser.py
pyngb/extractors/__init__.py
pyngb/extractors/base.py
pyngb/extractors/basic_fields.py
pyngb/extractors/manager.py
pyngb/extractors/mass.py
pyngb/extractors/specialized.py
pyngb/extractors/streams.py
pyngb/extractors/temperature.py
pyngb-0.1.1.dist-info/METADATA
pyngb-0.1.1.dist-info/WHEEL
pyngb-0.1.1.dist-info/entry_points.txt
pyngb-0.1.1.dist-info/licenses/LICENSE.txt
pyngb-0.1.1.dist-info/licenses/NOTICE
pyngb-0.1.1.dist-info/RECORD
