Metadata-Version: 2.4
Name: pyngb
Version: 0.1.1
Summary: Unofficial parser for NETZSCH STA (Simultaneous Thermal Analysis) NGB instrument binary files. Not affiliated with, endorsed by, or approved by NETZSCH-Gerätebau GmbH.
Project-URL: Homepage, https://github.com/GraysonBellamy/pyngb
Project-URL: Documentation, https://graysonbellamy.github.io/pyngb/
Project-URL: Repository, https://github.com/GraysonBellamy/pyngb.git
Project-URL: Issues, https://github.com/GraysonBellamy/pyngb/issues
Project-URL: Changelog, https://github.com/GraysonBellamy/pyngb/blob/main/CHANGELOG.md
Author-email: Grayson Bellamy <gbellamy@umd.edu>
License: MIT License
License-File: LICENSE.txt
License-File: NOTICE
Keywords: binary-parsing,netzsch,ngb,scientific-data,sta,thermal-analysis,unofficial
Classifier: Development Status :: 3 - Alpha
Classifier: Intended Audience :: Science/Research
Classifier: License :: OSI Approved :: MIT License
Classifier: Operating System :: OS Independent
Classifier: Programming Language :: Python :: 3
Classifier: Programming Language :: Python :: 3.9
Classifier: Programming Language :: Python :: 3.10
Classifier: Programming Language :: Python :: 3.11
Classifier: Programming Language :: Python :: 3.12
Classifier: Programming Language :: Python :: 3.13
Classifier: Topic :: Scientific/Engineering :: Chemistry
Classifier: Topic :: Scientific/Engineering :: Physics
Requires-Python: >=3.9
Requires-Dist: numpy>=1.20.0
Requires-Dist: polars>=0.20.0
Requires-Dist: pyarrow>=10.0.0
Requires-Dist: scipy>=1.13.1
Provides-Extra: build
Requires-Dist: build>=1.0.0; extra == 'build'
Requires-Dist: twine>=4.0.0; extra == 'build'
Provides-Extra: dev
Requires-Dist: bandit[toml]>=1.7.0; extra == 'dev'
Requires-Dist: mypy>=1.5.0; extra == 'dev'
Requires-Dist: pre-commit>=3.0.0; extra == 'dev'
Requires-Dist: pytest-benchmark>=4.0.0; extra == 'dev'
Requires-Dist: pytest-cov>=4.0.0; extra == 'dev'
Requires-Dist: pytest-mock>=3.10.0; extra == 'dev'
Requires-Dist: pytest>=7.0.0; extra == 'dev'
Requires-Dist: ruff>=0.1.0; extra == 'dev'
Requires-Dist: safety>=2.0.0; extra == 'dev'
Provides-Extra: docs
Requires-Dist: mkdocs-material>=9.0.0; extra == 'docs'
Requires-Dist: mkdocs>=1.5.0; extra == 'docs'
Requires-Dist: mkdocstrings[python]>=0.20.0; extra == 'docs'
Provides-Extra: performance
Requires-Dist: memory-profiler>=0.60.0; extra == 'performance'
Requires-Dist: psutil>=5.9.0; extra == 'performance'
Provides-Extra: test
Requires-Dist: pytest-benchmark>=4.0.0; extra == 'test'
Requires-Dist: pytest-cov>=4.0.0; extra == 'test'
Requires-Dist: pytest-mock>=3.10.0; extra == 'test'
Requires-Dist: pytest>=7.0.0; extra == 'test'
Provides-Extra: visualization
Requires-Dist: matplotlib>=3.5.0; extra == 'visualization'
Requires-Dist: seaborn>=0.11.0; extra == 'visualization'
